CHANGES.txt
CONTRIBUTORS.txt
MANIFEST.in
README.txt
setup.cfg
setup.py
Products/__init__.py
Products.Organization.egg-info/PKG-INFO
Products.Organization.egg-info/SOURCES.txt
Products.Organization.egg-info/dependency_links.txt
Products.Organization.egg-info/entry_points.txt
Products.Organization.egg-info/namespace_packages.txt
Products.Organization.egg-info/not-zip-safe
Products.Organization.egg-info/paster_plugins.txt
Products.Organization.egg-info/requires.txt
Products.Organization.egg-info/top_level.txt
Products/Organization/README.txt
Products/Organization/__init__.py
Products/Organization/config.py
Products/Organization/configure.zcml
Products/Organization/interfaces.py
Products/Organization/setuphandlers.py
Products/Organization/tests.py
Products/Organization/browser/__init__.py
Products/Organization/browser/configure.zcml
Products/Organization/browser/home.png
Products/Organization/browser/organization.pt
Products/Organization/content/__init__.py
Products/Organization/content/configure.zcml
Products/Organization/content/organization.py
Products/Organization/portlets/__init__.py
Products/Organization/portlets/configure.zcml
Products/Organization/profiles/default/browserlayer.xml
Products/Organization/profiles/default/diff_tool.xml
Products/Organization/profiles/default/factorytool.xml
Products/Organization/profiles/default/import_steps.xml
Products/Organization/profiles/default/metadata.xml
Products/Organization/profiles/default/portlets.xml
Products/Organization/profiles/default/rolemap.xml
Products/Organization/profiles/default/tinymce.xml
Products/Organization/profiles/default/types.xml
Products/Organization/profiles/default/types/Organization.xml
Products/Organization/tests/__init__.py
Products/Organization/tests/base.py
Products/Organization/tests/doc_tests.py
Products/Organization/tests/test_doctest.py
docs/HISTORY.txt
docs/INSTALL.txt
docs/LICENSE.GPL
docs/LICENSE.txt